{
  "_class": "group",
  "do_objectID": "D93941A2-DA7F-43BC-8CFD-C900ABA78C83",
  "exportOptions": {
    "_class": "exportOptions",
    "exportFormats": [
    ],
    "includedLayerIds": [
    ],
    "layerOptions": 0,
    "shouldTrim": false
  },
  "frame": {
    "_class": "rect",
    "constrainProportions": false,
    "height": 34,
    "width": 35,
    "x": 3.152081756743513,
    "y": 7.266963801785494
  },
  "hasClickThrough": false,
  "isFlippedHorizontal": false,
  "isFlippedVertical": false,
  "isLocked": false,
  "isVisible": true,
  "layerListExpandedType": 2,
  "layers": [
    {
      "class": "shapeGroup",
      "id": "82FF3732-357E-41F7-98AE-B030E15B54D4"
    },
    {
      "class": "shapeGroup",
      "id": "F6CF8098-FFA7-47B4-985F-071656CA2B6E"
    }
  ],
  "name": "Magic",
  "nameIsFixed": true,
  "resizingConstraint": 63,
  "resizingType": 0,
  "rotation": -12,
  "shouldBreakMaskChain": false,
  "style": {
    "sharedObjectID": "790A06A1-AA3A-48B1-AD10-58BD6F6039F5"
  },
  "userInfo": {
    "com.animaapp.stc-sketch-plugin": {
      "kModelPropertiesKey": {
      }
    }
  }
}